README.md
setup.py
settings_os/__connection.py
settings_os/__init__.py
settings_os/__logs.py
settings_os/__orm.py
settings_os/__webdriver_factory.py
settings_os.egg-info/PKG-INFO
settings_os.egg-info/SOURCES.txt
settings_os.egg-info/dependency_links.txt
settings_os.egg-info/requires.txt
settings_os.egg-info/top_level.txt