Metadata-Version: 2.4
Name: settings-os
Version: 1.4.5
Summary: Biblioteca de configurações uteis para projetos diversos.
Author: Miguel Tenório
Author-email: deepydev42@gmail.com
Classifier: Programming Language :: Python :: 3
Classifier: License :: OSI Approved :: MIT License
Classifier: Operating System :: OS Independent
Requires-Python: >=3.12
Requires-Dist: selenium
Requires-Dist: webdriver-manager
Requires-Dist: sqlalchemy
Requires-Dist: pymysql
Requires-Dist: psycopg2-binary
Requires-Dist: pyodbc
Requires-Dist: psutil
Requires-Dist: colorama
Dynamic: author
Dynamic: author-email
Dynamic: classifier
Dynamic: requires-dist
Dynamic: requires-python
Dynamic: summary
